{
    "args": {
        "graph_name": "dense_generated",
        "selected_algorithm": "Compact Forward",
        "with_doulion": true,
        "p": 0.9,
        "memorySize": "3000",
        "plotApproximate": true,
        "graph_path": "graphs/dense_generated.txt",
        "saved_as_directed": true,
        "numOfTriangles": 18981254,
        "paramName": "p",
        "apprParamValues": [
            "0.1",
            "0.2",
            "0.30000000000000004",
            "0.4",
            "0.5",
            "0.6",
            "0.7000000000000001",
            "0.8",
            "0.9"
        ]
    },
    "results": {
        "Doulion runtime": [
            0.14195847511291504,
            0.14083600044250488,
            0.14909982681274414,
            0.13407015800476074,
            0.1333777904510498,
            0.1323859691619873,
            0.12915301322937012,
            0.12071752548217773,
            0.11487936973571777
        ],
        "Compact Forward runtime": [
            0.37609052658081055,
            1.4153015613555908,
            3.1341381072998047,
            5.4294703006744385,
            8.22630524635315,
            11.560556650161743,
            15.557943344116211,
            19.79205870628357,
            24.790179014205933
        ],
        "Estimated Triangles": [
            18677999,
            19052124,
            18827555,
            18901765,
            18977208,
            18830546,
            19074533,
            18940445,
            18940253
        ],
        "Accuracy": [
            98.4023500238709,
            99.62662635461284,
            99.19026190553872,
            99.58122695687017,
            99.9786842323484,
            99.20601819192927,
            99.50857025728233,
            99.78500531366366,
            99.78399621168764
        ]
    }
}